CHANGES.rst
MANIFEST.in
README.txt
setup.cfg
setup.py
Products/__init__.py
Products.PloneHelpCenter.egg-info/PKG-INFO
Products.PloneHelpCenter.egg-info/SOURCES.txt
Products.PloneHelpCenter.egg-info/dependency_links.txt
Products.PloneHelpCenter.egg-info/namespace_packages.txt
Products.PloneHelpCenter.egg-info/not-zip-safe
Products.PloneHelpCenter.egg-info/requires.txt
Products.PloneHelpCenter.egg-info/top_level.txt
Products/PloneHelpCenter/LICENSE.GPL
Products/PloneHelpCenter/__init__.py
Products/PloneHelpCenter/config.py
Products/PloneHelpCenter/configure.zcml
Products/PloneHelpCenter/folderMigrate.py
Products/PloneHelpCenter/interfaces.py
Products/PloneHelpCenter/setuphandlers.py
Products/PloneHelpCenter/traversal.py
Products/PloneHelpCenter/update_locales.sh
Products/PloneHelpCenter/upgrades.py
Products/PloneHelpCenter/utils.py
Products/PloneHelpCenter/browser/__init__.py
Products/PloneHelpCenter/browser/configure.zcml
Products/PloneHelpCenter/browser/helpcenter.py
Products/PloneHelpCenter/browser/nextprevious.py
Products/PloneHelpCenter/browser/phc_attachments.py
Products/PloneHelpCenter/browser/phc_topic.pt
Products/PloneHelpCenter/browser/phccontent.py
Products/PloneHelpCenter/browser/phcfolder.py
Products/PloneHelpCenter/content/Definition.py
Products/PloneHelpCenter/content/ErrorReference.py
Products/PloneHelpCenter/content/ErrorReferenceFolder.py
Products/PloneHelpCenter/content/FAQ.py
Products/PloneHelpCenter/content/FAQFolder.py
Products/PloneHelpCenter/content/Glossary.py
Products/PloneHelpCenter/content/HelpCenter.py
Products/PloneHelpCenter/content/HowTo.py
Products/PloneHelpCenter/content/HowToFolder.py
Products/PloneHelpCenter/content/InstructionalVideo.py
Products/PloneHelpCenter/content/InstructionalVideoFolder.py
Products/PloneHelpCenter/content/KnowledgeBase.py
Products/PloneHelpCenter/content/LeafPage.py
Products/PloneHelpCenter/content/Link.py
Products/PloneHelpCenter/content/LinkFolder.py
Products/PloneHelpCenter/content/PHCContent.py
Products/PloneHelpCenter/content/PHCFolder.py
Products/PloneHelpCenter/content/ReferenceManual.py
Products/PloneHelpCenter/content/ReferenceManualFolder.py
Products/PloneHelpCenter/content/ReferenceManualPage.py
Products/PloneHelpCenter/content/ReferenceManualSection.py
Products/PloneHelpCenter/content/Tutorial.py
