Metadata-Version: 1.1
Name: Products.PloneHelpCenter
Version: 4.0
Summary: A simple help-desk style documentation product for Plone.
Home-page: https://github.com/collective/Products.PloneHelpCenter
Author: Israel Saeta Pérez
Author-email: dukebody@gmail.com
License: GPL
Keywords: Zope CMF Plone help documentation
Platform: UNKNOWN
Classifier: Framework :: Plone
Classifier: Framework :: Plone :: 4.2
Classifier: Framework :: Plone :: 4.3
Classifier: Framework :: Zope2
Classifier: Programming Language :: Python
Classifier: Programming Language :: Python :: 2.6
Classifier: Programming Language :: Python :: 2.7
